{
  "scenarioId": "weak_science_experiments_g5_30d__soak1",
  "profileRef": "p_weak_science_experiments",
  "mode": "deep",
  "tier": "deep",
  "seed": 103017,
  "anchorDate": "2026-05-19T08:00:00.000Z",
  "timeHorizonDays": 30,
  "generator": "deep-runner-v1",
  "stats": {
    "scenarioId": "weak_science_experiments_g5_30d__soak1",
    "sessionCount": 74,
    "questionTotal": 1184,
    "correctTotal": 419,
    "mistakeEventCount": 421,
    "subjectsTouched": [
      "science"
    ],
    "topicsBySubject": {
      "science": [
        "experiments"
      ]
    }
  },
  "validation": {
    "ok": true,
    "errors": [],
    "warnings": []
  },
  "warnings": [],
  "errors": [],
  "deepHorizonValidation": {
    "ok": true,
    "errors": []
  }
}