[
  {
    "studentId": "mass_mot8rgvm_0005_weak_english_g5",
    "grade": "g5",
    "subject": "science",
    "topic": "materials",
    "difficulty": "mixed",
    "questionId": "materials_24__mass_mot8rgvm_0005_weak_english_g5__0",
    "generatedQuestionId": "materials_24__mass_mot8rgvm_0005_weak_english_g5__0",
    "questionText": "מהו חומר רב-פעמי לעומת חד-פעמי?",
    "correctAnswer": "ערך ייחוס",
    "studentAnswer": "בחירה שגויה",
    "isCorrect": false,
    "mistakeType": "pattern_confusion",
    "responseTimeMs": 14242,
    "sessionId": "sess_mass_mot8rgvm_0005_weak_english_g5_0",
    "questionSource": "real",
    "contributesToParentReportEvidence": true
  },
  {
    "studentId": "mass_mot8rgvm_0005_weak_english_g5",
    "grade": "g5",
    "subject": "english",
    "topic": "grammar_basics",
    "difficulty": "mixed",
    "questionId": "q_mass_mot8rgvm_0005_weak_english_g5_1",
    "generatedQuestionId": "q_mass_mot8rgvm_0005_weak_english_g5_1",
    "questionText": "[סימולציה] תרגול grammar_basics ב-english (mixed)",
    "correctAnswer": "ערך ייחוס",
    "studentAnswer": "בחירה שגויה",
    "isCorrect": false,
    "mistakeType": "prerequisite_gap",
    "responseTimeMs": 20876,
    "sessionId": "sess_mass_mot8rgvm_0005_weak_english_g5_1",
    "questionSource": "placeholder",
    "contributesToParentReportEvidence": true
  },
  {
    "studentId": "mass_mot8rgvm_0005_weak_english_g5",
    "grade": "g5",
    "subject": "math",
    "topic": "place_value",
    "difficulty": "mixed",
    "questionId": "q_mass_mot8rgvm_0005_weak_english_g5_2",
    "generatedQuestionId": "q_mass_mot8rgvm_0005_weak_english_g5_2",
    "questionText": "[סימולציה] תרגול place_value ב-math (mixed)",
    "correctAnswer": "ערך ייחוס",
    "studentAnswer": "בחירה שגויה",
    "isCorrect": false,
    "mistakeType": "pattern_confusion",
    "responseTimeMs": 18305,
    "sessionId": "sess_mass_mot8rgvm_0005_weak_english_g5_2",
    "questionSource": "placeholder",
    "contributesToParentReportEvidence": true
  },
  {
    "studentId": "mass_mot8rgvm_0005_weak_english_g5",
    "grade": "g5",
    "subject": "english",
    "topic": "grammar_basics",
    "difficulty": "easy",
    "questionId": "q_mass_mot8rgvm_0005_weak_english_g5_3",
    "generatedQuestionId": "q_mass_mot8rgvm_0005_weak_english_g5_3",
    "questionText": "[סימולציה] תרגול grammar_basics ב-english (easy)",
    "correctAnswer": "ערך ייחוס",
    "studentAnswer": "בחירה שגויה",
    "isCorrect": false,
    "mistakeType": "wrong_operation",
    "responseTimeMs": 32869,
    "sessionId": "sess_mass_mot8rgvm_0005_weak_english_g5_3",
    "questionSource": "placeholder",
    "contributesToParentReportEvidence": true
  },
  {
    "studentId": "mass_mot8rgvm_0005_weak_english_g5",
    "grade": "g5",
    "subject": "geometry",
    "topic": "angles",
    "difficulty": "mixed",
    "questionId": "q_mass_mot8rgvm_0005_weak_english_g5_4",
    "generatedQuestionId": "q_mass_mot8rgvm_0005_weak_english_g5_4",
    "questionText": "[סימולציה] תרגול angles ב-geometry (mixed)",
    "correctAnswer": "בחירה נכונה",
    "studentAnswer": "בחירה נכונה",
    "isCorrect": true,
    "mistakeType": null,
    "responseTimeMs": 9233,
    "sessionId": "sess_mass_mot8rgvm_0005_weak_english_g5_4",
    "questionSource": "placeholder",
    "contributesToParentReportEvidence": true
  },
  {
    "studentId": "mass_mot8rgvm_0005_weak_english_g5",
    "grade": "g5",
    "subject": "english",
    "topic": "grammar_basics",
    "difficulty": "hard",
    "questionId": "q_mass_mot8rgvm_0005_weak_english_g5_5",
    "generatedQuestionId": "q_mass_mot8rgvm_0005_weak_english_g5_5",
    "questionText": "[סימולציה] תרגול grammar_basics ב-english (hard)",
    "correctAnswer": "ערך ייחוס",
    "studentAnswer": "בחירה שגויה",
    "isCorrect": false,
    "mistakeType": "misread_question",
    "responseTimeMs": 7859,
    "sessionId": "sess_mass_mot8rgvm_0005_weak_english_g5_5",
    "questionSource": "placeholder",
    "contributesToParentReportEvidence": true
  },
  {
    "studentId": "mass_mot8rgvm_0005_weak_english_g5",
    "grade": "g5",
    "subject": "moledet_geography",
    "topic": "map_reading",
    "difficulty": "easy",
    "questionId": "q_mass_mot8rgvm_0005_weak_english_g5_6",
    "generatedQuestionId": "q_mass_mot8rgvm_0005_weak_english_g5_6",
    "questionText": "[סימולציה] תרגול map_reading ב-moledet_geography (easy)",
    "correctAnswer": "ערך ייחוס",
    "studentAnswer": "בחירה שגויה",
    "isCorrect": false,
    "mistakeType": "pattern_confusion",
    "responseTimeMs": 23350,
    "sessionId": "sess_mass_mot8rgvm_0005_weak_english_g5_6",
    "questionSource": "placeholder",
    "contributesToParentReportEvidence": true
  },
  {
    "studentId": "mass_mot8rgvm_0005_weak_english_g5",
    "grade": "g5",
    "subject": "math",
    "topic": "addition",
    "difficulty": "mixed",
    "questionId": "q_mass_mot8rgvm_0005_weak_english_g5_7",
    "generatedQuestionId": "q_mass_mot8rgvm_0005_weak_english_g5_7",
    "questionText": "[סימולציה] תרגול addition ב-math (mixed)",
    "correctAnswer": "בחירה נכונה",
    "studentAnswer": "בחירה נכונה",
    "isCorrect": true,
    "mistakeType": null,
    "responseTimeMs": 44576,
    "sessionId": "sess_mass_mot8rgvm_0005_weak_english_g5_7",
    "questionSource": "placeholder",
    "contributesToParentReportEvidence": true
  },
  {
    "studentId": "mass_mot8rgvm_0005_weak_english_g5",
    "grade": "g5",
    "subject": "moledet_geography",
    "topic": "basic_geography",
    "difficulty": "medium",
    "questionId": "q_mass_mot8rgvm_0005_weak_english_g5_8",
    "generatedQuestionId": "q_mass_mot8rgvm_0005_weak_english_g5_8",
    "questionText": "[סימולציה] תרגול basic_geography ב-moledet_geography (medium)",
    "correctAnswer": "בחירה נכונה",
    "studentAnswer": "בחירה נכונה",
    "isCorrect": true,
    "mistakeType": null,
    "responseTimeMs": 28789,
    "sessionId": "sess_mass_mot8rgvm_0005_weak_english_g5_8",
    "questionSource": "placeholder",
    "contributesToParentReportEvidence": true
  },
  {
    "studentId": "mass_mot8rgvm_0005_weak_english_g5",
    "grade": "g5",
    "subject": "math",
    "topic": "word_problems",
    "difficulty": "easy",
    "questionId": "q_mass_mot8rgvm_0005_weak_english_g5_9",
    "generatedQuestionId": "q_mass_mot8rgvm_0005_weak_english_g5_9",
    "questionText": "[סימולציה] תרגול word_problems ב-math (easy)",
    "correctAnswer": "בחירה נכונה",
    "studentAnswer": "בחירה נכונה",
    "isCorrect": true,
    "mistakeType": null,
    "responseTimeMs": 21923,
    "sessionId": "sess_mass_mot8rgvm_0005_weak_english_g5_9",
    "questionSource": "placeholder",
    "contributesToParentReportEvidence": false
  },
  {
    "studentId": "mass_mot8rgvm_0005_weak_english_g5",
    "grade": "g5",
    "subject": "english",
    "topic": "vocabulary",
    "difficulty": "easy",
    "questionId": "q_mass_mot8rgvm_0005_weak_english_g5_10",
    "generatedQuestionId": "q_mass_mot8rgvm_0005_weak_english_g5_10",
    "questionText": "[סימולציה] תרגול vocabulary ב-english (easy)",
    "correctAnswer": "ערך ייחוס",
    "studentAnswer": "בחירה שגויה",
    "isCorrect": false,
    "mistakeType": "wrong_operation",
    "responseTimeMs": 37457,
    "sessionId": "sess_mass_mot8rgvm_0005_weak_english_g5_10",
    "questionSource": "placeholder",
    "contributesToParentReportEvidence": true
  },
  {
    "studentId": "mass_mot8rgvm_0005_weak_english_g5",
    "grade": "g5",
    "subject": "geometry",
    "topic": "area",
    "difficulty": "easy",
    "questionId": "q_mass_mot8rgvm_0005_weak_english_g5_11",
    "generatedQuestionId": "q_mass_mot8rgvm_0005_weak_english_g5_11",
    "questionText": "[סימולציה] תרגול area ב-geometry (easy)",
    "correctAnswer": "ערך ייחוס",
    "studentAnswer": "בחירה שגויה",
    "isCorrect": false,
    "mistakeType": "timeout_pressure",
    "responseTimeMs": 27822,
    "sessionId": "sess_mass_mot8rgvm_0005_weak_english_g5_11",
    "questionSource": "placeholder",
    "contributesToParentReportEvidence": true
  },
  {
    "studentId": "mass_mot8rgvm_0005_weak_english_g5",
    "grade": "g5",
    "subject": "geometry",
    "topic": "symmetry",
    "difficulty": "medium",
    "questionId": "q_mass_mot8rgvm_0005_weak_english_g5_12",
    "generatedQuestionId": "q_mass_mot8rgvm_0005_weak_english_g5_12",
    "questionText": "[סימולציה] תרגול symmetry ב-geometry (medium)",
    "correctAnswer": "בחירה נכונה",
    "studentAnswer": "בחירה נכונה",
    "isCorrect": true,
    "mistakeType": null,
    "responseTimeMs": 20248,
    "sessionId": "sess_mass_mot8rgvm_0005_weak_english_g5_12",
    "questionSource": "placeholder",
    "contributesToParentReportEvidence": false
  },
  {
    "studentId": "mass_mot8rgvm_0005_weak_english_g5",
    "grade": "g5",
    "subject": "english",
    "topic": "reading_comprehension",
    "difficulty": "medium",
    "questionId": "q_mass_mot8rgvm_0005_weak_english_g5_13",
    "generatedQuestionId": "q_mass_mot8rgvm_0005_weak_english_g5_13",
    "questionText": "[סימולציה] תרגול reading_comprehension ב-english (medium)",
    "correctAnswer": "ערך ייחוס",
    "studentAnswer": "בחירה שגויה",
    "isCorrect": false,
    "mistakeType": "careless",
    "responseTimeMs": 38616,
    "sessionId": "sess_mass_mot8rgvm_0005_weak_english_g5_13",
    "questionSource": "placeholder",
    "contributesToParentReportEvidence": true
  },
  {
    "studentId": "mass_mot8rgvm_0005_weak_english_g5",
    "grade": "g5",
    "subject": "moledet_geography",
    "topic": "basic_geography",
    "difficulty": "medium",
    "questionId": "q_mass_mot8rgvm_0005_weak_english_g5_14",
    "generatedQuestionId": "q_mass_mot8rgvm_0005_weak_english_g5_14",
    "questionText": "[סימולציה] תרגול basic_geography ב-moledet_geography (medium)",
    "correctAnswer": "ערך ייחוס",
    "studentAnswer": "בחירה שגויה",
    "isCorrect": false,
    "mistakeType": "conceptual",
    "responseTimeMs": 28425,
    "sessionId": "sess_mass_mot8rgvm_0005_weak_english_g5_14",
    "questionSource": "placeholder",
    "contributesToParentReportEvidence": true
  },
  {
    "studentId": "mass_mot8rgvm_0005_weak_english_g5",
    "grade": "g5",
    "subject": "science",
    "topic": "animals_plants",
    "difficulty": "medium",
    "questionId": "animals_3__mass_mot8rgvm_0005_weak_english_g5__15",
    "generatedQuestionId": "animals_3__mass_mot8rgvm_0005_weak_english_g5__15",
    "questionText": "זוחלים הם בעלי חיים שמכוסים בדרך כלל קשקשים ומטילים ביצים.",
    "correctAnswer": "ערך ייחוס",
    "studentAnswer": "בחירה שגויה",
    "isCorrect": false,
    "mistakeType": "wrong_operation",
    "responseTimeMs": 52834,
    "sessionId": "sess_mass_mot8rgvm_0005_weak_english_g5_15",
    "questionSource": "real",
    "contributesToParentReportEvidence": true
  },
  {
    "studentId": "mass_mot8rgvm_0005_weak_english_g5",
    "grade": "g5",
    "subject": "moledet_geography",
    "topic": "community",
    "difficulty": "hard",
    "questionId": "q_mass_mot8rgvm_0005_weak_english_g5_16",
    "generatedQuestionId": "q_mass_mot8rgvm_0005_weak_english_g5_16",
    "questionText": "[סימולציה] תרגול community ב-moledet_geography (hard)",
    "correctAnswer": "בחירה נכונה",
    "studentAnswer": "בחירה נכונה",
    "isCorrect": true,
    "mistakeType": null,
    "responseTimeMs": 14709,
    "sessionId": "sess_mass_mot8rgvm_0005_weak_english_g5_16",
    "questionSource": "placeholder",
    "contributesToParentReportEvidence": true
  },
  {
    "studentId": "mass_mot8rgvm_0005_weak_english_g5",
    "grade": "g5",
    "subject": "english",
    "topic": "vocabulary",
    "difficulty": "mixed",
    "questionId": "q_mass_mot8rgvm_0005_weak_english_g5_17",
    "generatedQuestionId": "q_mass_mot8rgvm_0005_weak_english_g5_17",
    "questionText": "[סימולציה] תרגול vocabulary ב-english (mixed)",
    "correctAnswer": "ערך ייחוס",
    "studentAnswer": "בחירה שגויה",
    "isCorrect": false,
    "mistakeType": "pattern_confusion",
    "responseTimeMs": 20793,
    "sessionId": "sess_mass_mot8rgvm_0005_weak_english_g5_17",
    "questionSource": "placeholder",
    "contributesToParentReportEvidence": false
  },
  {
    "studentId": "mass_mot8rgvm_0005_weak_english_g5",
    "grade": "g5",
    "subject": "moledet_geography",
    "topic": "map_reading",
    "difficulty": "medium",
    "questionId": "q_mass_mot8rgvm_0005_weak_english_g5_18",
    "generatedQuestionId": "q_mass_mot8rgvm_0005_weak_english_g5_18",
    "questionText": "[סימולציה] תרגול map_reading ב-moledet_geography (medium)",
    "correctAnswer": "ערך ייחוס",
    "studentAnswer": "בחירה שגויה",
    "isCorrect": false,
    "mistakeType": "pattern_confusion",
    "responseTimeMs": 25320,
    "sessionId": "sess_mass_mot8rgvm_0005_weak_english_g5_18",
    "questionSource": "placeholder",
    "contributesToParentReportEvidence": true
  },
  {
    "studentId": "mass_mot8rgvm_0005_weak_english_g5",
    "grade": "g5",
    "subject": "english",
    "topic": "matching",
    "difficulty": "easy",
    "questionId": "q_mass_mot8rgvm_0005_weak_english_g5_19",
    "generatedQuestionId": "q_mass_mot8rgvm_0005_weak_english_g5_19",
    "questionText": "[סימולציה] תרגול matching ב-english (easy)",
    "correctAnswer": "בחירה נכונה",
    "studentAnswer": "בחירה נכונה",
    "isCorrect": true,
    "mistakeType": null,
    "responseTimeMs": 30840,
    "sessionId": "sess_mass_mot8rgvm_0005_weak_english_g5_19",
    "questionSource": "placeholder",
    "contributesToParentReportEvidence": true
  },
  {
    "studentId": "mass_mot8rgvm_0005_weak_english_g5",
    "grade": "g5",
    "subject": "english",
    "topic": "vocabulary",
    "difficulty": "easy",
    "questionId": "q_mass_mot8rgvm_0005_weak_english_g5_20",
    "generatedQuestionId": "q_mass_mot8rgvm_0005_weak_english_g5_20",
    "questionText": "[סימולציה] תרגול vocabulary ב-english (easy)",
    "correctAnswer": "בחירה נכונה",
    "studentAnswer": "בחירה נכונה",
    "isCorrect": true,
    "mistakeType": null,
    "responseTimeMs": 45019,
    "sessionId": "sess_mass_mot8rgvm_0005_weak_english_g5_20",
    "questionSource": "placeholder",
    "contributesToParentReportEvidence": true
  },
  {
    "studentId": "mass_mot8rgvm_0005_weak_english_g5",
    "grade": "g5",
    "subject": "moledet_geography",
    "topic": "directions",
    "difficulty": "hard",
    "questionId": "q_mass_mot8rgvm_0005_weak_english_g5_21",
    "generatedQuestionId": "q_mass_mot8rgvm_0005_weak_english_g5_21",
    "questionText": "[סימולציה] תרגול directions ב-moledet_geography (hard)",
    "correctAnswer": "ערך ייחוס",
    "studentAnswer": "בחירה שגויה",
    "isCorrect": false,
    "mistakeType": "conceptual",
    "responseTimeMs": 34226,
    "sessionId": "sess_mass_mot8rgvm_0005_weak_english_g5_21",
    "questionSource": "placeholder",
    "contributesToParentReportEvidence": true
  },
  {
    "studentId": "mass_mot8rgvm_0005_weak_english_g5",
    "grade": "g5",
    "subject": "science",
    "topic": "body",
    "difficulty": "easy",
    "questionId": "body_34__mass_mot8rgvm_0005_weak_english_g5__22",
    "generatedQuestionId": "body_34__mass_mot8rgvm_0005_weak_english_g5__22",
    "questionText": "מה תפקיד הלבלב?",
    "correctAnswer": "בחירה נכונה",
    "studentAnswer": "בחירה נכונה",
    "isCorrect": true,
    "mistakeType": null,
    "responseTimeMs": 6351,
    "sessionId": "sess_mass_mot8rgvm_0005_weak_english_g5_22",
    "questionSource": "real",
    "contributesToParentReportEvidence": true
  },
  {
    "studentId": "mass_mot8rgvm_0005_weak_english_g5",
    "grade": "g5",
    "subject": "hebrew",
    "topic": "fact_vs_opinion",
    "difficulty": "easy",
    "questionId": "hebrew_archive_reading__mass_mot8rgvm_0005_weak_english_g5__23",
    "generatedQuestionId": "hebrew_archive_reading__mass_mot8rgvm_0005_weak_english_g5__23",
    "questionText": "קרא את הסיפור: 'ילדה אכלה אוכל בריא. היא שתתה מים. היא נהנתה מאוד.' מה העלילה?",
    "correctAnswer": "ערך ייחוס",
    "studentAnswer": "בחירה שגויה",
    "isCorrect": false,
    "mistakeType": "guess",
    "responseTimeMs": 24474,
    "sessionId": "sess_mass_mot8rgvm_0005_weak_english_g5_23",
    "questionSource": "real",
    "contributesToParentReportEvidence": true
  },
  {
    "studentId": "mass_mot8rgvm_0005_weak_english_g5",
    "grade": "g5",
    "subject": "hebrew",
    "topic": "fact_vs_opinion",
    "difficulty": "easy",
    "questionId": "hebrew_archive_reading__mass_mot8rgvm_0005_weak_english_g5__24",
    "generatedQuestionId": "hebrew_archive_reading__mass_mot8rgvm_0005_weak_english_g5__24",
    "questionText": "קרא את הסיפור: 'ילד יצא לטיול. הוא ראה פרחים יפים. הוא נהנה מהטיול.' מה העלילה?",
    "correctAnswer": "בחירה נכונה",
    "studentAnswer": "בחירה נכונה",
    "isCorrect": true,
    "mistakeType": null,
    "responseTimeMs": 48022,
    "sessionId": "sess_mass_mot8rgvm_0005_weak_english_g5_24",
    "questionSource": "real",
    "contributesToParentReportEvidence": true
  },
  {
    "studentId": "mass_mot8rgvm_0005_weak_english_g5",
    "grade": "g5",
    "subject": "moledet_geography",
    "topic": "map_reading",
    "difficulty": "easy",
    "questionId": "q_mass_mot8rgvm_0005_weak_english_g5_25",
    "generatedQuestionId": "q_mass_mot8rgvm_0005_weak_english_g5_25",
    "questionText": "[סימולציה] תרגול map_reading ב-moledet_geography (easy)",
    "correctAnswer": "בחירה נכונה",
    "studentAnswer": "בחירה נכונה",
    "isCorrect": true,
    "mistakeType": null,
    "responseTimeMs": 13634,
    "sessionId": "sess_mass_mot8rgvm_0005_weak_english_g5_25",
    "questionSource": "placeholder",
    "contributesToParentReportEvidence": true
  },
  {
    "studentId": "mass_mot8rgvm_0005_weak_english_g5",
    "grade": "g5",
    "subject": "english",
    "topic": "vocabulary",
    "difficulty": "easy",
    "questionId": "q_mass_mot8rgvm_0005_weak_english_g5_26",
    "generatedQuestionId": "q_mass_mot8rgvm_0005_weak_english_g5_26",
    "questionText": "[סימולציה] תרגול vocabulary ב-english (easy)",
    "correctAnswer": "בחירה נכונה",
    "studentAnswer": "בחירה נכונה",
    "isCorrect": true,
    "mistakeType": null,
    "responseTimeMs": 36713,
    "sessionId": "sess_mass_mot8rgvm_0005_weak_english_g5_26",
    "questionSource": "placeholder",
    "contributesToParentReportEvidence": true
  },
  {
    "studentId": "mass_mot8rgvm_0005_weak_english_g5",
    "grade": "g5",
    "subject": "hebrew",
    "topic": "reading_comprehension",
    "difficulty": "mixed",
    "questionId": "hebrew_archive_reading__mass_mot8rgvm_0005_weak_english_g5__27",
    "generatedQuestionId": "hebrew_archive_reading__mass_mot8rgvm_0005_weak_english_g5__27",
    "questionText": "קרא את הטקסט המידעי: 'השמש היא כוכב. היא נותנת אור וחום. בלי השמש לא יהיה חיים על כדור הארץ.' מה הרעיון המרכזי?",
    "correctAnswer": "בחירה נכונה",
    "studentAnswer": "בחירה נכונה",
    "isCorrect": true,
    "mistakeType": null,
    "responseTimeMs": 9873,
    "sessionId": "sess_mass_mot8rgvm_0005_weak_english_g5_27",
    "questionSource": "real",
    "contributesToParentReportEvidence": true
  },
  {
    "studentId": "mass_mot8rgvm_0005_weak_english_g5",
    "grade": "g5",
    "subject": "science",
    "topic": "body",
    "difficulty": "easy",
    "questionId": "body_34__mass_mot8rgvm_0005_weak_english_g5__28",
    "generatedQuestionId": "body_34__mass_mot8rgvm_0005_weak_english_g5__28",
    "questionText": "מה תפקיד הלבלב?",
    "correctAnswer": "ערך ייחוס",
    "studentAnswer": "בחירה שגויה",
    "isCorrect": false,
    "mistakeType": "wrong_operation",
    "responseTimeMs": 53455,
    "sessionId": "sess_mass_mot8rgvm_0005_weak_english_g5_28",
    "questionSource": "real",
    "contributesToParentReportEvidence": true
  },
  {
    "studentId": "mass_mot8rgvm_0005_weak_english_g5",
    "grade": "g5",
    "subject": "geometry",
    "topic": "shapes",
    "difficulty": "mixed",
    "questionId": "q_mass_mot8rgvm_0005_weak_english_g5_29",
    "generatedQuestionId": "q_mass_mot8rgvm_0005_weak_english_g5_29",
    "questionText": "[סימולציה] תרגול shapes ב-geometry (mixed)",
    "correctAnswer": "ערך ייחוס",
    "studentAnswer": "בחירה שגויה",
    "isCorrect": false,
    "mistakeType": "conceptual",
    "responseTimeMs": 46748,
    "sessionId": "sess_mass_mot8rgvm_0005_weak_english_g5_29",
    "questionSource": "placeholder",
    "contributesToParentReportEvidence": true
  },
  {
    "studentId": "mass_mot8rgvm_0005_weak_english_g5",
    "grade": "g5",
    "subject": "hebrew",
    "topic": "inference",
    "difficulty": "easy",
    "questionId": "hebrew_archive_reading__mass_mot8rgvm_0005_weak_english_g5__30",
    "generatedQuestionId": "hebrew_archive_reading__mass_mot8rgvm_0005_weak_english_g5__30",
    "questionText": "קרא את הסיפור: 'ילדה הרגישה גאווה. היא הצליחה במבחן. היא נהנתה מאוד.' מה העלילה?",
    "correctAnswer": "בחירה נכונה",
    "studentAnswer": "בחירה נכונה",
    "isCorrect": true,
    "mistakeType": null,
    "responseTimeMs": 43253,
    "sessionId": "sess_mass_mot8rgvm_0005_weak_english_g5_30",
    "questionSource": "real",
    "contributesToParentReportEvidence": true
  },
  {
    "studentId": "mass_mot8rgvm_0005_weak_english_g5",
    "grade": "g5",
    "subject": "hebrew",
    "topic": "sequence",
    "difficulty": "medium",
    "questionId": "hebrew_archive_reading__mass_mot8rgvm_0005_weak_english_g5__31",
    "generatedQuestionId": "hebrew_archive_reading__mass_mot8rgvm_0005_weak_english_g5__31",
    "questionText": "קרא את הסיפור: 'ילד שתל צמח. הצמח גדל יפה. הוא נהנה מאוד.' מה העלילה?",
    "correctAnswer": "ערך ייחוס",
    "studentAnswer": "בחירה שגויה",
    "isCorrect": false,
    "mistakeType": "pattern_confusion",
    "responseTimeMs": 7650,
    "sessionId": "sess_mass_mot8rgvm_0005_weak_english_g5_31",
    "questionSource": "real",
    "contributesToParentReportEvidence": false
  },
  {
    "studentId": "mass_mot8rgvm_0005_weak_english_g5",
    "grade": "g5",
    "subject": "moledet_geography",
    "topic": "map_reading",
    "difficulty": "medium",
    "questionId": "q_mass_mot8rgvm_0005_weak_english_g5_32",
    "generatedQuestionId": "q_mass_mot8rgvm_0005_weak_english_g5_32",
    "questionText": "[סימולציה] תרגול map_reading ב-moledet_geography (medium)",
    "correctAnswer": "ערך ייחוס",
    "studentAnswer": "בחירה שגויה",
    "isCorrect": false,
    "mistakeType": "guess",
    "responseTimeMs": 18003,
    "sessionId": "sess_mass_mot8rgvm_0005_weak_english_g5_32",
    "questionSource": "placeholder",
    "contributesToParentReportEvidence": true
  },
  {
    "studentId": "mass_mot8rgvm_0005_weak_english_g5",
    "grade": "g5",
    "subject": "moledet_geography",
    "topic": "community",
    "difficulty": "easy",
    "questionId": "q_mass_mot8rgvm_0005_weak_english_g5_33",
    "generatedQuestionId": "q_mass_mot8rgvm_0005_weak_english_g5_33",
    "questionText": "[סימולציה] תרגול community ב-moledet_geography (easy)",
    "correctAnswer": "ערך ייחוס",
    "studentAnswer": "בחירה שגויה",
    "isCorrect": false,
    "mistakeType": "wrong_operation",
    "responseTimeMs": 5382,
    "sessionId": "sess_mass_mot8rgvm_0005_weak_english_g5_33",
    "questionSource": "placeholder",
    "contributesToParentReportEvidence": true
  },
  {
    "studentId": "mass_mot8rgvm_0005_weak_english_g5",
    "grade": "g5",
    "subject": "moledet_geography",
    "topic": "map_reading",
    "difficulty": "hard",
    "questionId": "q_mass_mot8rgvm_0005_weak_english_g5_34",
    "generatedQuestionId": "q_mass_mot8rgvm_0005_weak_english_g5_34",
    "questionText": "[סימולציה] תרגול map_reading ב-moledet_geography (hard)",
    "correctAnswer": "ערך ייחוס",
    "studentAnswer": "בחירה שגויה",
    "isCorrect": false,
    "mistakeType": "pattern_confusion",
    "responseTimeMs": 5652,
    "sessionId": "sess_mass_mot8rgvm_0005_weak_english_g5_34",
    "questionSource": "placeholder",
    "contributesToParentReportEvidence": true
  },
  {
    "studentId": "mass_mot8rgvm_0005_weak_english_g5",
    "grade": "g5",
    "subject": "geometry",
    "topic": "angles",
    "difficulty": "mixed",
    "questionId": "q_mass_mot8rgvm_0005_weak_english_g5_35",
    "generatedQuestionId": "q_mass_mot8rgvm_0005_weak_english_g5_35",
    "questionText": "[סימולציה] תרגול angles ב-geometry (mixed)",
    "correctAnswer": "בחירה נכונה",
    "studentAnswer": "בחירה נכונה",
    "isCorrect": true,
    "mistakeType": null,
    "responseTimeMs": 46634,
    "sessionId": "sess_mass_mot8rgvm_0005_weak_english_g5_35",
    "questionSource": "placeholder",
    "contributesToParentReportEvidence": false
  },
  {
    "studentId": "mass_mot8rgvm_0005_weak_english_g5",
    "grade": "g5",
    "subject": "english",
    "topic": "vocabulary",
    "difficulty": "medium",
    "questionId": "q_mass_mot8rgvm_0005_weak_english_g5_36",
    "generatedQuestionId": "q_mass_mot8rgvm_0005_weak_english_g5_36",
    "questionText": "[סימולציה] תרגול vocabulary ב-english (medium)",
    "correctAnswer": "בחירה נכונה",
    "studentAnswer": "בחירה נכונה",
    "isCorrect": true,
    "mistakeType": null,
    "responseTimeMs": 46962,
    "sessionId": "sess_mass_mot8rgvm_0005_weak_english_g5_36",
    "questionSource": "placeholder",
    "contributesToParentReportEvidence": true
  },
  {
    "studentId": "mass_mot8rgvm_0005_weak_english_g5",
    "grade": "g5",
    "subject": "english",
    "topic": "grammar_basics",
    "difficulty": "mixed",
    "questionId": "q_mass_mot8rgvm_0005_weak_english_g5_37",
    "generatedQuestionId": "q_mass_mot8rgvm_0005_weak_english_g5_37",
    "questionText": "[סימולציה] תרגול grammar_basics ב-english (mixed)",
    "correctAnswer": "בחירה נכונה",
    "studentAnswer": "בחירה נכונה",
    "isCorrect": true,
    "mistakeType": null,
    "responseTimeMs": 31847,
    "sessionId": "sess_mass_mot8rgvm_0005_weak_english_g5_37",
    "questionSource": "placeholder",
    "contributesToParentReportEvidence": true
  },
  {
    "studentId": "mass_mot8rgvm_0005_weak_english_g5",
    "grade": "g5",
    "subject": "hebrew",
    "topic": "vocabulary",
    "difficulty": "mixed",
    "questionId": "hebrew_archive_vocabulary__mass_mot8rgvm_0005_weak_english_g5__38",
    "generatedQuestionId": "hebrew_archive_vocabulary__mass_mot8rgvm_0005_weak_english_g5__38",
    "questionText": "מה משפחת המילה 'כתיבה'?",
    "correctAnswer": "ערך ייחוס",
    "studentAnswer": "בחירה שגויה",
    "isCorrect": false,
    "mistakeType": "wrong_operation",
    "responseTimeMs": 37069,
    "sessionId": "sess_mass_mot8rgvm_0005_weak_english_g5_38",
    "questionSource": "real",
    "contributesToParentReportEvidence": true
  },
  {
    "studentId": "mass_mot8rgvm_0005_weak_english_g5",
    "grade": "g5",
    "subject": "hebrew",
    "topic": "sequence",
    "difficulty": "easy",
    "questionId": "hebrew_archive_reading__mass_mot8rgvm_0005_weak_english_g5__39",
    "generatedQuestionId": "hebrew_archive_reading__mass_mot8rgvm_0005_weak_english_g5__39",
    "questionText": "קרא את הסיפור: 'ילדה קראה ספר. הספר היה מעניין. היא נהנתה מאוד.' מה העלילה?",
    "correctAnswer": "ערך ייחוס",
    "studentAnswer": "בחירה שגויה",
    "isCorrect": false,
    "mistakeType": "pattern_confusion",
    "responseTimeMs": 18651,
    "sessionId": "sess_mass_mot8rgvm_0005_weak_english_g5_39",
    "questionSource": "real",
    "contributesToParentReportEvidence": true
  },
  {
    "studentId": "mass_mot8rgvm_0005_weak_english_g5",
    "grade": "g5",
    "subject": "geometry",
    "topic": "angles",
    "difficulty": "easy",
    "questionId": "q_mass_mot8rgvm_0005_weak_english_g5_40",
    "generatedQuestionId": "q_mass_mot8rgvm_0005_weak_english_g5_40",
    "questionText": "[סימולציה] תרגול angles ב-geometry (easy)",
    "correctAnswer": "ערך ייחוס",
    "studentAnswer": "בחירה שגויה",
    "isCorrect": false,
    "mistakeType": "misread_question",
    "responseTimeMs": 16480,
    "sessionId": "sess_mass_mot8rgvm_0005_weak_english_g5_40",
    "questionSource": "placeholder",
    "contributesToParentReportEvidence": true
  },
  {
    "studentId": "mass_mot8rgvm_0005_weak_english_g5",
    "grade": "g5",
    "subject": "geometry",
    "topic": "area",
    "difficulty": "easy",
    "questionId": "q_mass_mot8rgvm_0005_weak_english_g5_41",
    "generatedQuestionId": "q_mass_mot8rgvm_0005_weak_english_g5_41",
    "questionText": "[סימולציה] תרגול area ב-geometry (easy)",
    "correctAnswer": "בחירה נכונה",
    "studentAnswer": "בחירה נכונה",
    "isCorrect": true,
    "mistakeType": null,
    "responseTimeMs": 15162,
    "sessionId": "sess_mass_mot8rgvm_0005_weak_english_g5_41",
    "questionSource": "placeholder",
    "contributesToParentReportEvidence": true
  },
  {
    "studentId": "mass_mot8rgvm_0005_weak_english_g5",
    "grade": "g5",
    "subject": "moledet_geography",
    "topic": "map_reading",
    "difficulty": "easy",
    "questionId": "q_mass_mot8rgvm_0005_weak_english_g5_42",
    "generatedQuestionId": "q_mass_mot8rgvm_0005_weak_english_g5_42",
    "questionText": "[סימולציה] תרגול map_reading ב-moledet_geography (easy)",
    "correctAnswer": "בחירה נכונה",
    "studentAnswer": "בחירה נכונה",
    "isCorrect": true,
    "mistakeType": null,
    "responseTimeMs": 19520,
    "sessionId": "sess_mass_mot8rgvm_0005_weak_english_g5_42",
    "questionSource": "placeholder",
    "contributesToParentReportEvidence": true
  },
  {
    "studentId": "mass_mot8rgvm_0005_weak_english_g5",
    "grade": "g5",
    "subject": "hebrew",
    "topic": "fact_vs_opinion",
    "difficulty": "hard",
    "questionId": "hebrew_archive_reading__mass_mot8rgvm_0005_weak_english_g5__43",
    "generatedQuestionId": "hebrew_archive_reading__mass_mot8rgvm_0005_weak_english_g5__43",
    "questionText": "קרא את הסיפור: 'ילד שתל צמח. הצמח גדל יפה. הוא נהנה מאוד.' מה העלילה?",
    "correctAnswer": "בחירה נכונה",
    "studentAnswer": "בחירה נכונה",
    "isCorrect": true,
    "mistakeType": null,
    "responseTimeMs": 54636,
    "sessionId": "sess_mass_mot8rgvm_0005_weak_english_g5_43",
    "questionSource": "real",
    "contributesToParentReportEvidence": true
  },
  {
    "studentId": "mass_mot8rgvm_0005_weak_english_g5",
    "grade": "g5",
    "subject": "hebrew",
    "topic": "main_idea",
    "difficulty": "easy",
    "questionId": "hebrew_archive_reading__mass_mot8rgvm_0005_weak_english_g5__44",
    "generatedQuestionId": "hebrew_archive_reading__mass_mot8rgvm_0005_weak_english_g5__44",
    "questionText": "קרא את הטקסט המידעי: 'ההצלחה חשובה מאוד. היא עוזרת להרגיש טוב. היא עוזרת להרגיש גאווה.' מה הרעיון המרכזי?",
    "correctAnswer": "ערך ייחוס",
    "studentAnswer": "בחירה שגויה",
    "isCorrect": false,
    "mistakeType": "timeout_pressure",
    "responseTimeMs": 9326,
    "sessionId": "sess_mass_mot8rgvm_0005_weak_english_g5_44",
    "questionSource": "real",
    "contributesToParentReportEvidence": true
  },
  {
    "studentId": "mass_mot8rgvm_0005_weak_english_g5",
    "grade": "g5",
    "subject": "moledet_geography",
    "topic": "community",
    "difficulty": "mixed",
    "questionId": "q_mass_mot8rgvm_0005_weak_english_g5_45",
    "generatedQuestionId": "q_mass_mot8rgvm_0005_weak_english_g5_45",
    "questionText": "[סימולציה] תרגול community ב-moledet_geography (mixed)",
    "correctAnswer": "בחירה נכונה",
    "studentAnswer": "בחירה נכונה",
    "isCorrect": true,
    "mistakeType": null,
    "responseTimeMs": 44108,
    "sessionId": "sess_mass_mot8rgvm_0005_weak_english_g5_45",
    "questionSource": "placeholder",
    "contributesToParentReportEvidence": true
  },
  {
    "studentId": "mass_mot8rgvm_0005_weak_english_g5",
    "grade": "g5",
    "subject": "math",
    "topic": "addition",
    "difficulty": "hard",
    "questionId": "q_mass_mot8rgvm_0005_weak_english_g5_46",
    "generatedQuestionId": "q_mass_mot8rgvm_0005_weak_english_g5_46",
    "questionText": "[סימולציה] תרגול addition ב-math (hard)",
    "correctAnswer": "ערך ייחוס",
    "studentAnswer": "בחירה שגויה",
    "isCorrect": false,
    "mistakeType": "pattern_confusion",
    "responseTimeMs": 5809,
    "sessionId": "sess_mass_mot8rgvm_0005_weak_english_g5_46",
    "questionSource": "placeholder",
    "contributesToParentReportEvidence": true
  },
  {
    "studentId": "mass_mot8rgvm_0005_weak_english_g5",
    "grade": "g5",
    "subject": "geometry",
    "topic": "angles",
    "difficulty": "hard",
    "questionId": "q_mass_mot8rgvm_0005_weak_english_g5_47",
    "generatedQuestionId": "q_mass_mot8rgvm_0005_weak_english_g5_47",
    "questionText": "[סימולציה] תרגול angles ב-geometry (hard)",
    "correctAnswer": "בחירה נכונה",
    "studentAnswer": "בחירה נכונה",
    "isCorrect": true,
    "mistakeType": null,
    "responseTimeMs": 6435,
    "sessionId": "sess_mass_mot8rgvm_0005_weak_english_g5_47",
    "questionSource": "placeholder",
    "contributesToParentReportEvidence": true
  },
  {
    "studentId": "mass_mot8rgvm_0005_weak_english_g5",
    "grade": "g5",
    "subject": "science",
    "topic": "basic_experiments",
    "difficulty": "hard",
    "questionId": "animals_25__mass_mot8rgvm_0005_weak_english_g5__48",
    "generatedQuestionId": "animals_25__mass_mot8rgvm_0005_weak_english_g5__48",
    "questionText": "מהו דפוס הסוואה?",
    "correctAnswer": "ערך ייחוס",
    "studentAnswer": "בחירה שגויה",
    "isCorrect": false,
    "mistakeType": "misread_question",
    "responseTimeMs": 39721,
    "sessionId": "sess_mass_mot8rgvm_0005_weak_english_g5_48",
    "questionSource": "real",
    "contributesToParentReportEvidence": true
  },
  {
    "studentId": "mass_mot8rgvm_0005_weak_english_g5",
    "grade": "g5",
    "subject": "english",
    "topic": "vocabulary",
    "difficulty": "mixed",
    "questionId": "q_mass_mot8rgvm_0005_weak_english_g5_49",
    "generatedQuestionId": "q_mass_mot8rgvm_0005_weak_english_g5_49",
    "questionText": "[סימולציה] תרגול vocabulary ב-english (mixed)",
    "correctAnswer": "בחירה נכונה",
    "studentAnswer": "בחירה נכונה",
    "isCorrect": true,
    "mistakeType": null,
    "responseTimeMs": 37796,
    "sessionId": "sess_mass_mot8rgvm_0005_weak_english_g5_49",
    "questionSource": "placeholder",
    "contributesToParentReportEvidence": true
  },
  {
    "studentId": "mass_mot8rgvm_0005_weak_english_g5",
    "grade": "g5",
    "subject": "science",
    "topic": "body",
    "difficulty": "medium",
    "questionId": "body_33__mass_mot8rgvm_0005_weak_english_g5__50",
    "generatedQuestionId": "body_33__mass_mot8rgvm_0005_weak_english_g5__50",
    "questionText": "מה תפקיד בלוטת התריס?",
    "correctAnswer": "בחירה נכונה",
    "studentAnswer": "בחירה נכונה",
    "isCorrect": true,
    "mistakeType": null,
    "responseTimeMs": 11801,
    "sessionId": "sess_mass_mot8rgvm_0005_weak_english_g5_50",
    "questionSource": "real",
    "contributesToParentReportEvidence": true
  },
  {
    "studentId": "mass_mot8rgvm_0005_weak_english_g5",
    "grade": "g5",
    "subject": "hebrew",
    "topic": "main_idea",
    "difficulty": "mixed",
    "questionId": "hebrew_archive_reading__mass_mot8rgvm_0005_weak_english_g5__51",
    "generatedQuestionId": "hebrew_archive_reading__mass_mot8rgvm_0005_weak_english_g5__51",
    "questionText": "קרא את הטקסט המידעי: 'הציורים חשובים מאוד. הם עוזרים להביע רגשות. הם עוזרים להרגיש טוב.' מה הרעיון המרכזי?",
    "correctAnswer": "בחירה נכונה",
    "studentAnswer": "בחירה נכונה",
    "isCorrect": true,
    "mistakeType": null,
    "responseTimeMs": 24347,
    "sessionId": "sess_mass_mot8rgvm_0005_weak_english_g5_51",
    "questionSource": "real",
    "contributesToParentReportEvidence": true
  },
  {
    "studentId": "mass_mot8rgvm_0005_weak_english_g5",
    "grade": "g5",
    "subject": "hebrew",
    "topic": "reading_comprehension",
    "difficulty": "easy",
    "questionId": "hebrew_archive_reading__mass_mot8rgvm_0005_weak_english_g5__52",
    "generatedQuestionId": "hebrew_archive_reading__mass_mot8rgvm_0005_weak_english_g5__52",
    "questionText": "קרא את הטקסט המידעי: 'המשפחה חשובה מאוד. היא עוזרת להרגיש בטוח. היא עוזרת להרגיש אהוב.' מה הרעיון המרכזי?",
    "correctAnswer": "ערך ייחוס",
    "studentAnswer": "בחירה שגויה",
    "isCorrect": false,
    "mistakeType": "conceptual",
    "responseTimeMs": 33448,
    "sessionId": "sess_mass_mot8rgvm_0005_weak_english_g5_52",
    "questionSource": "real",
    "contributesToParentReportEvidence": true
  },
  {
    "studentId": "mass_mot8rgvm_0005_weak_english_g5",
    "grade": "g5",
    "subject": "hebrew",
    "topic": "main_idea",
    "difficulty": "easy",
    "questionId": "hebrew_archive_reading__mass_mot8rgvm_0005_weak_english_g5__53",
    "generatedQuestionId": "hebrew_archive_reading__mass_mot8rgvm_0005_weak_english_g5__53",
    "questionText": "קרא את הטקסט המידעי: 'הלמידה חשובה מאוד. היא עוזרת להבין. היא עוזרת להצליח.' מה הרעיון המרכזי?",
    "correctAnswer": "בחירה נכונה",
    "studentAnswer": "בחירה נכונה",
    "isCorrect": true,
    "mistakeType": null,
    "responseTimeMs": 34841,
    "sessionId": "sess_mass_mot8rgvm_0005_weak_english_g5_53",
    "questionSource": "real",
    "contributesToParentReportEvidence": true
  },
  {
    "studentId": "mass_mot8rgvm_0005_weak_english_g5",
    "grade": "g5",
    "subject": "moledet_geography",
    "topic": "basic_geography",
    "difficulty": "easy",
    "questionId": "q_mass_mot8rgvm_0005_weak_english_g5_54",
    "generatedQuestionId": "q_mass_mot8rgvm_0005_weak_english_g5_54",
    "questionText": "[סימולציה] תרגול basic_geography ב-moledet_geography (easy)",
    "correctAnswer": "בחירה נכונה",
    "studentAnswer": "בחירה נכונה",
    "isCorrect": true,
    "mistakeType": null,
    "responseTimeMs": 14369,
    "sessionId": "sess_mass_mot8rgvm_0005_weak_english_g5_54",
    "questionSource": "placeholder",
    "contributesToParentReportEvidence": true
  },
  {
    "studentId": "mass_mot8rgvm_0005_weak_english_g5",
    "grade": "g5",
    "subject": "english",
    "topic": "matching",
    "difficulty": "hard",
    "questionId": "q_mass_mot8rgvm_0005_weak_english_g5_55",
    "generatedQuestionId": "q_mass_mot8rgvm_0005_weak_english_g5_55",
    "questionText": "[סימולציה] תרגול matching ב-english (hard)",
    "correctAnswer": "בחירה נכונה",
    "studentAnswer": "בחירה נכונה",
    "isCorrect": true,
    "mistakeType": null,
    "responseTimeMs": 47023,
    "sessionId": "sess_mass_mot8rgvm_0005_weak_english_g5_55",
    "questionSource": "placeholder",
    "contributesToParentReportEvidence": true
  },
  {
    "studentId": "mass_mot8rgvm_0005_weak_english_g5",
    "grade": "g5",
    "subject": "moledet_geography",
    "topic": "map_reading",
    "difficulty": "hard",
    "questionId": "q_mass_mot8rgvm_0005_weak_english_g5_56",
    "generatedQuestionId": "q_mass_mot8rgvm_0005_weak_english_g5_56",
    "questionText": "[סימולציה] תרגול map_reading ב-moledet_geography (hard)",
    "correctAnswer": "ערך ייחוס",
    "studentAnswer": "בחירה שגויה",
    "isCorrect": false,
    "mistakeType": "timeout_pressure",
    "responseTimeMs": 39828,
    "sessionId": "sess_mass_mot8rgvm_0005_weak_english_g5_56",
    "questionSource": "placeholder",
    "contributesToParentReportEvidence": true
  },
  {
    "studentId": "mass_mot8rgvm_0005_weak_english_g5",
    "grade": "g5",
    "subject": "english",
    "topic": "sentence_understanding",
    "difficulty": "medium",
    "questionId": "q_mass_mot8rgvm_0005_weak_english_g5_57",
    "generatedQuestionId": "q_mass_mot8rgvm_0005_weak_english_g5_57",
    "questionText": "[סימולציה] תרגול sentence_understanding ב-english (medium)",
    "correctAnswer": "ערך ייחוס",
    "studentAnswer": "בחירה שגויה",
    "isCorrect": false,
    "mistakeType": "guess",
    "responseTimeMs": 5335,
    "sessionId": "sess_mass_mot8rgvm_0005_weak_english_g5_57",
    "questionSource": "placeholder",
    "contributesToParentReportEvidence": true
  },
  {
    "studentId": "mass_mot8rgvm_0005_weak_english_g5",
    "grade": "g5",
    "subject": "science",
    "topic": "body",
    "difficulty": "medium",
    "questionId": "body_31__mass_mot8rgvm_0005_weak_english_g5__58",
    "generatedQuestionId": "body_31__mass_mot8rgvm_0005_weak_english_g5__58",
    "questionText": "מה תפקיד הכבד?",
    "correctAnswer": "ערך ייחוס",
    "studentAnswer": "בחירה שגויה",
    "isCorrect": false,
    "mistakeType": "careless",
    "responseTimeMs": 42577,
    "sessionId": "sess_mass_mot8rgvm_0005_weak_english_g5_58",
    "questionSource": "real",
    "contributesToParentReportEvidence": true
  },
  {
    "studentId": "mass_mot8rgvm_0005_weak_english_g5",
    "grade": "g5",
    "subject": "geometry",
    "topic": "shapes",
    "difficulty": "hard",
    "questionId": "q_mass_mot8rgvm_0005_weak_english_g5_59",
    "generatedQuestionId": "q_mass_mot8rgvm_0005_weak_english_g5_59",
    "questionText": "[סימולציה] תרגול shapes ב-geometry (hard)",
    "correctAnswer": "בחירה נכונה",
    "studentAnswer": "בחירה נכונה",
    "isCorrect": true,
    "mistakeType": null,
    "responseTimeMs": 7582,
    "sessionId": "sess_mass_mot8rgvm_0005_weak_english_g5_59",
    "questionSource": "placeholder",
    "contributesToParentReportEvidence": true
  },
  {
    "studentId": "mass_mot8rgvm_0005_weak_english_g5",
    "grade": "g5",
    "subject": "hebrew",
    "topic": "sequence",
    "difficulty": "mixed",
    "questionId": "hebrew_archive_reading__mass_mot8rgvm_0005_weak_english_g5__60",
    "generatedQuestionId": "hebrew_archive_reading__mass_mot8rgvm_0005_weak_english_g5__60",
    "questionText": "קרא את הטקסט המידעי: 'ההצלחה חשובה מאוד. היא עוזרת להרגיש טוב. היא עוזרת להרגיש גאווה.' מה הרעיון המרכזי?",
    "correctAnswer": "בחירה נכונה",
    "studentAnswer": "בחירה נכונה",
    "isCorrect": true,
    "mistakeType": null,
    "responseTimeMs": 44719,
    "sessionId": "sess_mass_mot8rgvm_0005_weak_english_g5_60",
    "questionSource": "real",
    "contributesToParentReportEvidence": true
  },
  {
    "studentId": "mass_mot8rgvm_0005_weak_english_g5",
    "grade": "g5",
    "subject": "math",
    "topic": "multiplication",
    "difficulty": "hard",
    "questionId": "q_mass_mot8rgvm_0005_weak_english_g5_61",
    "generatedQuestionId": "q_mass_mot8rgvm_0005_weak_english_g5_61",
    "questionText": "[סימולציה] תרגול multiplication ב-math (hard)",
    "correctAnswer": "ערך ייחוס",
    "studentAnswer": "בחירה שגויה",
    "isCorrect": false,
    "mistakeType": "timeout_pressure",
    "responseTimeMs": 40313,
    "sessionId": "sess_mass_mot8rgvm_0005_weak_english_g5_61",
    "questionSource": "placeholder",
    "contributesToParentReportEvidence": true
  },
  {
    "studentId": "mass_mot8rgvm_0005_weak_english_g5",
    "grade": "g5",
    "subject": "english",
    "topic": "matching",
    "difficulty": "mixed",
    "questionId": "q_mass_mot8rgvm_0005_weak_english_g5_62",
    "generatedQuestionId": "q_mass_mot8rgvm_0005_weak_english_g5_62",
    "questionText": "[סימולציה] תרגול matching ב-english (mixed)",
    "correctAnswer": "בחירה נכונה",
    "studentAnswer": "בחירה נכונה",
    "isCorrect": true,
    "mistakeType": null,
    "responseTimeMs": 23695,
    "sessionId": "sess_mass_mot8rgvm_0005_weak_english_g5_62",
    "questionSource": "placeholder",
    "contributesToParentReportEvidence": true
  },
  {
    "studentId": "mass_mot8rgvm_0005_weak_english_g5",
    "grade": "g5",
    "subject": "english",
    "topic": "vocabulary",
    "difficulty": "mixed",
    "questionId": "q_mass_mot8rgvm_0005_weak_english_g5_63",
    "generatedQuestionId": "q_mass_mot8rgvm_0005_weak_english_g5_63",
    "questionText": "[סימולציה] תרגול vocabulary ב-english (mixed)",
    "correctAnswer": "ערך ייחוס",
    "studentAnswer": "בחירה שגויה",
    "isCorrect": false,
    "mistakeType": "misread_question",
    "responseTimeMs": 32845,
    "sessionId": "sess_mass_mot8rgvm_0005_weak_english_g5_63",
    "questionSource": "placeholder",
    "contributesToParentReportEvidence": true
  },
  {
    "studentId": "mass_mot8rgvm_0005_weak_english_g5",
    "grade": "g5",
    "subject": "geometry",
    "topic": "shapes",
    "difficulty": "mixed",
    "questionId": "q_mass_mot8rgvm_0005_weak_english_g5_64",
    "generatedQuestionId": "q_mass_mot8rgvm_0005_weak_english_g5_64",
    "questionText": "[סימולציה] תרגול shapes ב-geometry (mixed)",
    "correctAnswer": "ערך ייחוס",
    "studentAnswer": "בחירה שגויה",
    "isCorrect": false,
    "mistakeType": "guess",
    "responseTimeMs": 45359,
    "sessionId": "sess_mass_mot8rgvm_0005_weak_english_g5_64",
    "questionSource": "placeholder",
    "contributesToParentReportEvidence": true
  },
  {
    "studentId": "mass_mot8rgvm_0005_weak_english_g5",
    "grade": "g5",
    "subject": "science",
    "topic": "environment",
    "difficulty": "easy",
    "questionId": "science_remaining_g56_easy_environment__mass_mot8rgvm_0005_weak_english_g5__65",
    "generatedQuestionId": "science_remaining_g56_easy_environment__mass_mot8rgvm_0005_weak_english_g5__65",
    "questionText": "למה חשוב לחסוך במים בבית ובקהילה?",
    "correctAnswer": "בחירה נכונה",
    "studentAnswer": "בחירה נכונה",
    "isCorrect": true,
    "mistakeType": null,
    "responseTimeMs": 36006,
    "sessionId": "sess_mass_mot8rgvm_0005_weak_english_g5_65",
    "questionSource": "real",
    "contributesToParentReportEvidence": true
  },
  {
    "studentId": "mass_mot8rgvm_0005_weak_english_g5",
    "grade": "g5",
    "subject": "hebrew",
    "topic": "fact_vs_opinion",
    "difficulty": "hard",
    "questionId": "hebrew_archive_reading__mass_mot8rgvm_0005_weak_english_g5__66",
    "generatedQuestionId": "hebrew_archive_reading__mass_mot8rgvm_0005_weak_english_g5__66",
    "questionText": "קרא את הסיפור: 'ילדה למדה דברים חדשים. היא הבינה אותם. היא נהנתה מאוד.' מה העלילה?",
    "correctAnswer": "בחירה נכונה",
    "studentAnswer": "בחירה נכונה",
    "isCorrect": true,
    "mistakeType": null,
    "responseTimeMs": 16107,
    "sessionId": "sess_mass_mot8rgvm_0005_weak_english_g5_66",
    "questionSource": "real",
    "contributesToParentReportEvidence": true
  },
  {
    "studentId": "mass_mot8rgvm_0005_weak_english_g5",
    "grade": "g5",
    "subject": "moledet_geography",
    "topic": "basic_geography",
    "difficulty": "medium",
    "questionId": "q_mass_mot8rgvm_0005_weak_english_g5_67",
    "generatedQuestionId": "q_mass_mot8rgvm_0005_weak_english_g5_67",
    "questionText": "[סימולציה] תרגול basic_geography ב-moledet_geography (medium)",
    "correctAnswer": "ערך ייחוס",
    "studentAnswer": "בחירה שגויה",
    "isCorrect": false,
    "mistakeType": "careless",
    "responseTimeMs": 31153,
    "sessionId": "sess_mass_mot8rgvm_0005_weak_english_g5_67",
    "questionSource": "placeholder",
    "contributesToParentReportEvidence": true
  },
  {
    "studentId": "mass_mot8rgvm_0005_weak_english_g5",
    "grade": "g5",
    "subject": "math",
    "topic": "comparison",
    "difficulty": "hard",
    "questionId": "q_mass_mot8rgvm_0005_weak_english_g5_68",
    "generatedQuestionId": "q_mass_mot8rgvm_0005_weak_english_g5_68",
    "questionText": "[סימולציה] תרגול comparison ב-math (hard)",
    "correctAnswer": "בחירה נכונה",
    "studentAnswer": "בחירה נכונה",
    "isCorrect": true,
    "mistakeType": null,
    "responseTimeMs": 40782,
    "sessionId": "sess_mass_mot8rgvm_0005_weak_english_g5_68",
    "questionSource": "placeholder",
    "contributesToParentReportEvidence": true
  },
  {
    "studentId": "mass_mot8rgvm_0005_weak_english_g5",
    "grade": "g5",
    "subject": "math",
    "topic": "multiplication",
    "difficulty": "medium",
    "questionId": "q_mass_mot8rgvm_0005_weak_english_g5_69",
    "generatedQuestionId": "q_mass_mot8rgvm_0005_weak_english_g5_69",
    "questionText": "[סימולציה] תרגול multiplication ב-math (medium)",
    "correctAnswer": "ערך ייחוס",
    "studentAnswer": "בחירה שגויה",
    "isCorrect": false,
    "mistakeType": "timeout_pressure",
    "responseTimeMs": 40578,
    "sessionId": "sess_mass_mot8rgvm_0005_weak_english_g5_69",
    "questionSource": "placeholder",
    "contributesToParentReportEvidence": true
  },
  {
    "studentId": "mass_mot8rgvm_0005_weak_english_g5",
    "grade": "g5",
    "subject": "moledet_geography",
    "topic": "community",
    "difficulty": "medium",
    "questionId": "q_mass_mot8rgvm_0005_weak_english_g5_70",
    "generatedQuestionId": "q_mass_mot8rgvm_0005_weak_english_g5_70",
    "questionText": "[סימולציה] תרגול community ב-moledet_geography (medium)",
    "correctAnswer": "בחירה נכונה",
    "studentAnswer": "בחירה נכונה",
    "isCorrect": true,
    "mistakeType": null,
    "responseTimeMs": 49631,
    "sessionId": "sess_mass_mot8rgvm_0005_weak_english_g5_70",
    "questionSource": "placeholder",
    "contributesToParentReportEvidence": false
  },
  {
    "studentId": "mass_mot8rgvm_0005_weak_english_g5",
    "grade": "g5",
    "subject": "math",
    "topic": "addition",
    "difficulty": "medium",
    "questionId": "q_mass_mot8rgvm_0005_weak_english_g5_71",
    "generatedQuestionId": "q_mass_mot8rgvm_0005_weak_english_g5_71",
    "questionText": "[סימולציה] תרגול addition ב-math (medium)",
    "correctAnswer": "בחירה נכונה",
    "studentAnswer": "בחירה נכונה",
    "isCorrect": true,
    "mistakeType": null,
    "responseTimeMs": 4566,
    "sessionId": "sess_mass_mot8rgvm_0005_weak_english_g5_71",
    "questionSource": "placeholder",
    "contributesToParentReportEvidence": true
  },
  {
    "studentId": "mass_mot8rgvm_0005_weak_english_g5",
    "grade": "g5",
    "subject": "moledet_geography",
    "topic": "directions",
    "difficulty": "easy",
    "questionId": "q_mass_mot8rgvm_0005_weak_english_g5_72",
    "generatedQuestionId": "q_mass_mot8rgvm_0005_weak_english_g5_72",
    "questionText": "[סימולציה] תרגול directions ב-moledet_geography (easy)",
    "correctAnswer": "בחירה נכונה",
    "studentAnswer": "בחירה נכונה",
    "isCorrect": true,
    "mistakeType": null,
    "responseTimeMs": 22337,
    "sessionId": "sess_mass_mot8rgvm_0005_weak_english_g5_72",
    "questionSource": "placeholder",
    "contributesToParentReportEvidence": true
  },
  {
    "studentId": "mass_mot8rgvm_0005_weak_english_g5",
    "grade": "g5",
    "subject": "moledet_geography",
    "topic": "directions",
    "difficulty": "hard",
    "questionId": "q_mass_mot8rgvm_0005_weak_english_g5_73",
    "generatedQuestionId": "q_mass_mot8rgvm_0005_weak_english_g5_73",
    "questionText": "[סימולציה] תרגול directions ב-moledet_geography (hard)",
    "correctAnswer": "בחירה נכונה",
    "studentAnswer": "בחירה נכונה",
    "isCorrect": true,
    "mistakeType": null,
    "responseTimeMs": 15416,
    "sessionId": "sess_mass_mot8rgvm_0005_weak_english_g5_73",
    "questionSource": "placeholder",
    "contributesToParentReportEvidence": true
  },
  {
    "studentId": "mass_mot8rgvm_0005_weak_english_g5",
    "grade": "g5",
    "subject": "science",
    "topic": "environment",
    "difficulty": "easy",
    "questionId": "env_36__mass_mot8rgvm_0005_weak_english_g5__74",
    "generatedQuestionId": "env_36__mass_mot8rgvm_0005_weak_english_g5__74",
    "questionText": "למה 'אנרגיה מתחדשת' לא פותרת אוטומטית את כל נזקי הסביבה?",
    "correctAnswer": "בחירה נכונה",
    "studentAnswer": "בחירה נכונה",
    "isCorrect": true,
    "mistakeType": null,
    "responseTimeMs": 42301,
    "sessionId": "sess_mass_mot8rgvm_0005_weak_english_g5_74",
    "questionSource": "real",
    "contributesToParentReportEvidence": true
  },
  {
    "studentId": "mass_mot8rgvm_0005_weak_english_g5",
    "grade": "g5",
    "subject": "science",
    "topic": "environment",
    "difficulty": "hard",
    "questionId": "science_remaining_g56_easy_environment__mass_mot8rgvm_0005_weak_english_g5__75",
    "generatedQuestionId": "science_remaining_g56_easy_environment__mass_mot8rgvm_0005_weak_english_g5__75",
    "questionText": "למה חשוב לחסוך במים בבית ובקהילה?",
    "correctAnswer": "ערך ייחוס",
    "studentAnswer": "בחירה שגויה",
    "isCorrect": false,
    "mistakeType": "prerequisite_gap",
    "responseTimeMs": 44191,
    "sessionId": "sess_mass_mot8rgvm_0005_weak_english_g5_75",
    "questionSource": "real",
    "contributesToParentReportEvidence": false
  },
  {
    "studentId": "mass_mot8rgvm_0005_weak_english_g5",
    "grade": "g5",
    "subject": "geometry",
    "topic": "symmetry",
    "difficulty": "easy",
    "questionId": "q_mass_mot8rgvm_0005_weak_english_g5_76",
    "generatedQuestionId": "q_mass_mot8rgvm_0005_weak_english_g5_76",
    "questionText": "[סימולציה] תרגול symmetry ב-geometry (easy)",
    "correctAnswer": "בחירה נכונה",
    "studentAnswer": "בחירה נכונה",
    "isCorrect": true,
    "mistakeType": null,
    "responseTimeMs": 20383,
    "sessionId": "sess_mass_mot8rgvm_0005_weak_english_g5_76",
    "questionSource": "placeholder",
    "contributesToParentReportEvidence": true
  },
  {
    "studentId": "mass_mot8rgvm_0005_weak_english_g5",
    "grade": "g5",
    "subject": "science",
    "topic": "materials",
    "difficulty": "easy",
    "questionId": "materials_13__mass_mot8rgvm_0005_weak_english_g5__77",
    "generatedQuestionId": "materials_13__mass_mot8rgvm_0005_weak_english_g5__77",
    "questionText": "מהו שינוי כימי?",
    "correctAnswer": "בחירה נכונה",
    "studentAnswer": "בחירה נכונה",
    "isCorrect": true,
    "mistakeType": null,
    "responseTimeMs": 28614,
    "sessionId": "sess_mass_mot8rgvm_0005_weak_english_g5_77",
    "questionSource": "real",
    "contributesToParentReportEvidence": true
  },
  {
    "studentId": "mass_mot8rgvm_0005_weak_english_g5",
    "grade": "g5",
    "subject": "math",
    "topic": "comparison",
    "difficulty": "hard",
    "questionId": "q_mass_mot8rgvm_0005_weak_english_g5_78",
    "generatedQuestionId": "q_mass_mot8rgvm_0005_weak_english_g5_78",
    "questionText": "[סימולציה] תרגול comparison ב-math (hard)",
    "correctAnswer": "ערך ייחוס",
    "studentAnswer": "בחירה שגויה",
    "isCorrect": false,
    "mistakeType": "timeout_pressure",
    "responseTimeMs": 32135,
    "sessionId": "sess_mass_mot8rgvm_0005_weak_english_g5_78",
    "questionSource": "placeholder",
    "contributesToParentReportEvidence": true
  },
  {
    "studentId": "mass_mot8rgvm_0005_weak_english_g5",
    "grade": "g5",
    "subject": "math",
    "topic": "division",
    "difficulty": "hard",
    "questionId": "q_mass_mot8rgvm_0005_weak_english_g5_79",
    "generatedQuestionId": "q_mass_mot8rgvm_0005_weak_english_g5_79",
    "questionText": "[סימולציה] תרגול division ב-math (hard)",
    "correctAnswer": "ערך ייחוס",
    "studentAnswer": "בחירה שגויה",
    "isCorrect": false,
    "mistakeType": "timeout_pressure",
    "responseTimeMs": 17563,
    "sessionId": "sess_mass_mot8rgvm_0005_weak_english_g5_79",
    "questionSource": "placeholder",
    "contributesToParentReportEvidence": true
  },
  {
    "studentId": "mass_mot8rgvm_0005_weak_english_g5",
    "grade": "g5",
    "subject": "english",
    "topic": "sentence_understanding",
    "difficulty": "easy",
    "questionId": "q_mass_mot8rgvm_0005_weak_english_g5_80",
    "generatedQuestionId": "q_mass_mot8rgvm_0005_weak_english_g5_80",
    "questionText": "[סימולציה] תרגול sentence_understanding ב-english (easy)",
    "correctAnswer": "בחירה נכונה",
    "studentAnswer": "בחירה נכונה",
    "isCorrect": true,
    "mistakeType": null,
    "responseTimeMs": 23081,
    "sessionId": "sess_mass_mot8rgvm_0005_weak_english_g5_80",
    "questionSource": "placeholder",
    "contributesToParentReportEvidence": true
  },
  {
    "studentId": "mass_mot8rgvm_0005_weak_english_g5",
    "grade": "g5",
    "subject": "english",
    "topic": "vocabulary",
    "difficulty": "medium",
    "questionId": "q_mass_mot8rgvm_0005_weak_english_g5_81",
    "generatedQuestionId": "q_mass_mot8rgvm_0005_weak_english_g5_81",
    "questionText": "[סימולציה] תרגול vocabulary ב-english (medium)",
    "correctAnswer": "בחירה נכונה",
    "studentAnswer": "בחירה נכונה",
    "isCorrect": true,
    "mistakeType": null,
    "responseTimeMs": 33115,
    "sessionId": "sess_mass_mot8rgvm_0005_weak_english_g5_81",
    "questionSource": "placeholder",
    "contributesToParentReportEvidence": true
  },
  {
    "studentId": "mass_mot8rgvm_0005_weak_english_g5",
    "grade": "g5",
    "subject": "geometry",
    "topic": "angles",
    "difficulty": "hard",
    "questionId": "q_mass_mot8rgvm_0005_weak_english_g5_82",
    "generatedQuestionId": "q_mass_mot8rgvm_0005_weak_english_g5_82",
    "questionText": "[סימולציה] תרגול angles ב-geometry (hard)",
    "correctAnswer": "בחירה נכונה",
    "studentAnswer": "בחירה נכונה",
    "isCorrect": true,
    "mistakeType": null,
    "responseTimeMs": 8075,
    "sessionId": "sess_mass_mot8rgvm_0005_weak_english_g5_82",
    "questionSource": "placeholder",
    "contributesToParentReportEvidence": true
  },
  {
    "studentId": "mass_mot8rgvm_0005_weak_english_g5",
    "grade": "g5",
    "subject": "moledet_geography",
    "topic": "places",
    "difficulty": "mixed",
    "questionId": "q_mass_mot8rgvm_0005_weak_english_g5_83",
    "generatedQuestionId": "q_mass_mot8rgvm_0005_weak_english_g5_83",
    "questionText": "[סימולציה] תרגול places ב-moledet_geography (mixed)",
    "correctAnswer": "ערך ייחוס",
    "studentAnswer": "בחירה שגויה",
    "isCorrect": false,
    "mistakeType": "wrong_operation",
    "responseTimeMs": 30345,
    "sessionId": "sess_mass_mot8rgvm_0005_weak_english_g5_83",
    "questionSource": "placeholder",
    "contributesToParentReportEvidence": true
  },
  {
    "studentId": "mass_mot8rgvm_0005_weak_english_g5",
    "grade": "g5",
    "subject": "english",
    "topic": "reading_comprehension",
    "difficulty": "hard",
    "questionId": "q_mass_mot8rgvm_0005_weak_english_g5_84",
    "generatedQuestionId": "q_mass_mot8rgvm_0005_weak_english_g5_84",
    "questionText": "[סימולציה] תרגול reading_comprehension ב-english (hard)",
    "correctAnswer": "בחירה נכונה",
    "studentAnswer": "בחירה נכונה",
    "isCorrect": true,
    "mistakeType": null,
    "responseTimeMs": 15190,
    "sessionId": "sess_mass_mot8rgvm_0005_weak_english_g5_84",
    "questionSource": "placeholder",
    "contributesToParentReportEvidence": true
  },
  {
    "studentId": "mass_mot8rgvm_0005_weak_english_g5",
    "grade": "g5",
    "subject": "math",
    "topic": "addition",
    "difficulty": "medium",
    "questionId": "q_mass_mot8rgvm_0005_weak_english_g5_85",
    "generatedQuestionId": "q_mass_mot8rgvm_0005_weak_english_g5_85",
    "questionText": "[סימולציה] תרגול addition ב-math (medium)",
    "correctAnswer": "ערך ייחוס",
    "studentAnswer": "בחירה שגויה",
    "isCorrect": false,
    "mistakeType": "wrong_operation",
    "responseTimeMs": 26169,
    "sessionId": "sess_mass_mot8rgvm_0005_weak_english_g5_85",
    "questionSource": "placeholder",
    "contributesToParentReportEvidence": true
  },
  {
    "studentId": "mass_mot8rgvm_0005_weak_english_g5",
    "grade": "g5",
    "subject": "english",
    "topic": "reading_comprehension",
    "difficulty": "hard",
    "questionId": "q_mass_mot8rgvm_0005_weak_english_g5_86",
    "generatedQuestionId": "q_mass_mot8rgvm_0005_weak_english_g5_86",
    "questionText": "[סימולציה] תרגול reading_comprehension ב-english (hard)",
    "correctAnswer": "בחירה נכונה",
    "studentAnswer": "בחירה נכונה",
    "isCorrect": true,
    "mistakeType": null,
    "responseTimeMs": 43085,
    "sessionId": "sess_mass_mot8rgvm_0005_weak_english_g5_86",
    "questionSource": "placeholder",
    "contributesToParentReportEvidence": true
  },
  {
    "studentId": "mass_mot8rgvm_0005_weak_english_g5",
    "grade": "g5",
    "subject": "math",
    "topic": "fractions",
    "difficulty": "easy",
    "questionId": "q_mass_mot8rgvm_0005_weak_english_g5_87",
    "generatedQuestionId": "q_mass_mot8rgvm_0005_weak_english_g5_87",
    "questionText": "[סימולציה] תרגול fractions ב-math (easy)",
    "correctAnswer": "בחירה נכונה",
    "studentAnswer": "בחירה נכונה",
    "isCorrect": true,
    "mistakeType": null,
    "responseTimeMs": 27087,
    "sessionId": "sess_mass_mot8rgvm_0005_weak_english_g5_87",
    "questionSource": "placeholder",
    "contributesToParentReportEvidence": true
  },
  {
    "studentId": "mass_mot8rgvm_0005_weak_english_g5",
    "grade": "g5",
    "subject": "hebrew",
    "topic": "fact_vs_opinion",
    "difficulty": "easy",
    "questionId": "hebrew_archive_reading__mass_mot8rgvm_0005_weak_english_g5__88",
    "generatedQuestionId": "hebrew_archive_reading__mass_mot8rgvm_0005_weak_english_g5__88",
    "questionText": "קרא את הסיפור: 'ילד שיחק כדורגל. הוא שיחק עם חברים. הוא נהנה מאוד.' מה העלילה?",
    "correctAnswer": "ערך ייחוס",
    "studentAnswer": "בחירה שגויה",
    "isCorrect": false,
    "mistakeType": "misread_question",
    "responseTimeMs": 33250,
    "sessionId": "sess_mass_mot8rgvm_0005_weak_english_g5_88",
    "questionSource": "real",
    "contributesToParentReportEvidence": true
  },
  {
    "studentId": "mass_mot8rgvm_0005_weak_english_g5",
    "grade": "g5",
    "subject": "moledet_geography",
    "topic": "places",
    "difficulty": "hard",
    "questionId": "q_mass_mot8rgvm_0005_weak_english_g5_89",
    "generatedQuestionId": "q_mass_mot8rgvm_0005_weak_english_g5_89",
    "questionText": "[סימולציה] תרגול places ב-moledet_geography (hard)",
    "correctAnswer": "ערך ייחוס",
    "studentAnswer": "בחירה שגויה",
    "isCorrect": false,
    "mistakeType": "conceptual",
    "responseTimeMs": 51931,
    "sessionId": "sess_mass_mot8rgvm_0005_weak_english_g5_89",
    "questionSource": "placeholder",
    "contributesToParentReportEvidence": true
  },
  {
    "studentId": "mass_mot8rgvm_0005_weak_english_g5",
    "grade": "g5",
    "subject": "english",
    "topic": "matching",
    "difficulty": "hard",
    "questionId": "q_mass_mot8rgvm_0005_weak_english_g5_90",
    "generatedQuestionId": "q_mass_mot8rgvm_0005_weak_english_g5_90",
    "questionText": "[סימולציה] תרגול matching ב-english (hard)",
    "correctAnswer": "ערך ייחוס",
    "studentAnswer": "בחירה שגויה",
    "isCorrect": false,
    "mistakeType": "guess",
    "responseTimeMs": 44769,
    "sessionId": "sess_mass_mot8rgvm_0005_weak_english_g5_90",
    "questionSource": "placeholder",
    "contributesToParentReportEvidence": true
  },
  {
    "studentId": "mass_mot8rgvm_0005_weak_english_g5",
    "grade": "g5",
    "subject": "moledet_geography",
    "topic": "places",
    "difficulty": "easy",
    "questionId": "q_mass_mot8rgvm_0005_weak_english_g5_91",
    "generatedQuestionId": "q_mass_mot8rgvm_0005_weak_english_g5_91",
    "questionText": "[סימולציה] תרגול places ב-moledet_geography (easy)",
    "correctAnswer": "ערך ייחוס",
    "studentAnswer": "בחירה שגויה",
    "isCorrect": false,
    "mistakeType": "careless",
    "responseTimeMs": 47325,
    "sessionId": "sess_mass_mot8rgvm_0005_weak_english_g5_91",
    "questionSource": "placeholder",
    "contributesToParentReportEvidence": true
  },
  {
    "studentId": "mass_mot8rgvm_0005_weak_english_g5",
    "grade": "g5",
    "subject": "science",
    "topic": "animals_plants",
    "difficulty": "mixed",
    "questionId": "animals_4__mass_mot8rgvm_0005_weak_english_g5__92",
    "generatedQuestionId": "animals_4__mass_mot8rgvm_0005_weak_english_g5__92",
    "questionText": "מהי 'שרשרת מזון'?",
    "correctAnswer": "ערך ייחוס",
    "studentAnswer": "בחירה שגויה",
    "isCorrect": false,
    "mistakeType": "misread_question",
    "responseTimeMs": 11785,
    "sessionId": "sess_mass_mot8rgvm_0005_weak_english_g5_92",
    "questionSource": "real",
    "contributesToParentReportEvidence": true
  },
  {
    "studentId": "mass_mot8rgvm_0005_weak_english_g5",
    "grade": "g5",
    "subject": "science",
    "topic": "materials",
    "difficulty": "medium",
    "questionId": "materials_24__mass_mot8rgvm_0005_weak_english_g5__93",
    "generatedQuestionId": "materials_24__mass_mot8rgvm_0005_weak_english_g5__93",
    "questionText": "מהו חומר רב-פעמי לעומת חד-פעמי?",
    "correctAnswer": "ערך ייחוס",
    "studentAnswer": "בחירה שגויה",
    "isCorrect": false,
    "mistakeType": "careless",
    "responseTimeMs": 54963,
    "sessionId": "sess_mass_mot8rgvm_0005_weak_english_g5_93",
    "questionSource": "real",
    "contributesToParentReportEvidence": true
  },
  {
    "studentId": "mass_mot8rgvm_0005_weak_english_g5",
    "grade": "g5",
    "subject": "science",
    "topic": "materials",
    "difficulty": "mixed",
    "questionId": "materials_3__mass_mot8rgvm_0005_weak_english_g5__94",
    "generatedQuestionId": "materials_3__mass_mot8rgvm_0005_weak_english_g5__94",
    "questionText": "פלסטיק הוא חומר מעשה ידי אדם, שאינו נמצא בטבע כפי שהוא.",
    "correctAnswer": "בחירה נכונה",
    "studentAnswer": "בחירה נכונה",
    "isCorrect": true,
    "mistakeType": null,
    "responseTimeMs": 35065,
    "sessionId": "sess_mass_mot8rgvm_0005_weak_english_g5_94",
    "questionSource": "real",
    "contributesToParentReportEvidence": true
  },
  {
    "studentId": "mass_mot8rgvm_0005_weak_english_g5",
    "grade": "g5",
    "subject": "english",
    "topic": "grammar_basics",
    "difficulty": "medium",
    "questionId": "q_mass_mot8rgvm_0005_weak_english_g5_95",
    "generatedQuestionId": "q_mass_mot8rgvm_0005_weak_english_g5_95",
    "questionText": "[סימולציה] תרגול grammar_basics ב-english (medium)",
    "correctAnswer": "ערך ייחוס",
    "studentAnswer": "בחירה שגויה",
    "isCorrect": false,
    "mistakeType": "guess",
    "responseTimeMs": 10541,
    "sessionId": "sess_mass_mot8rgvm_0005_weak_english_g5_95",
    "questionSource": "placeholder",
    "contributesToParentReportEvidence": true
  },
  {
    "studentId": "mass_mot8rgvm_0005_weak_english_g5",
    "grade": "g5",
    "subject": "moledet_geography",
    "topic": "basic_geography",
    "difficulty": "mixed",
    "questionId": "q_mass_mot8rgvm_0005_weak_english_g5_96",
    "generatedQuestionId": "q_mass_mot8rgvm_0005_weak_english_g5_96",
    "questionText": "[סימולציה] תרגול basic_geography ב-moledet_geography (mixed)",
    "correctAnswer": "ערך ייחוס",
    "studentAnswer": "בחירה שגויה",
    "isCorrect": false,
    "mistakeType": "careless",
    "responseTimeMs": 6528,
    "sessionId": "sess_mass_mot8rgvm_0005_weak_english_g5_96",
    "questionSource": "placeholder",
    "contributesToParentReportEvidence": true
  },
  {
    "studentId": "mass_mot8rgvm_0005_weak_english_g5",
    "grade": "g5",
    "subject": "english",
    "topic": "reading_comprehension",
    "difficulty": "medium",
    "questionId": "q_mass_mot8rgvm_0005_weak_english_g5_97",
    "generatedQuestionId": "q_mass_mot8rgvm_0005_weak_english_g5_97",
    "questionText": "[סימולציה] תרגול reading_comprehension ב-english (medium)",
    "correctAnswer": "ערך ייחוס",
    "studentAnswer": "בחירה שגויה",
    "isCorrect": false,
    "mistakeType": "prerequisite_gap",
    "responseTimeMs": 14591,
    "sessionId": "sess_mass_mot8rgvm_0005_weak_english_g5_97",
    "questionSource": "placeholder",
    "contributesToParentReportEvidence": true
  },
  {
    "studentId": "mass_mot8rgvm_0005_weak_english_g5",
    "grade": "g5",
    "subject": "english",
    "topic": "grammar_basics",
    "difficulty": "easy",
    "questionId": "q_mass_mot8rgvm_0005_weak_english_g5_98",
    "generatedQuestionId": "q_mass_mot8rgvm_0005_weak_english_g5_98",
    "questionText": "[סימולציה] תרגול grammar_basics ב-english (easy)",
    "correctAnswer": "ערך ייחוס",
    "studentAnswer": "בחירה שגויה",
    "isCorrect": false,
    "mistakeType": "misread_question",
    "responseTimeMs": 28644,
    "sessionId": "sess_mass_mot8rgvm_0005_weak_english_g5_98",
    "questionSource": "placeholder",
    "contributesToParentReportEvidence": false
  },
  {
    "studentId": "mass_mot8rgvm_0005_weak_english_g5",
    "grade": "g5",
    "subject": "hebrew",
    "topic": "main_idea",
    "difficulty": "medium",
    "questionId": "hebrew_archive_reading__mass_mot8rgvm_0005_weak_english_g5__99",
    "generatedQuestionId": "hebrew_archive_reading__mass_mot8rgvm_0005_weak_english_g5__99",
    "questionText": "קרא את הטקסט המידעי: 'העצים חשובים לטבע. הם נותנים צל. הם עוזרים לנשום.' מה הרעיון המרכזי?",
    "correctAnswer": "ערך ייחוס",
    "studentAnswer": "בחירה שגויה",
    "isCorrect": false,
    "mistakeType": "pattern_confusion",
    "responseTimeMs": 37350,
    "sessionId": "sess_mass_mot8rgvm_0005_weak_english_g5_99",
    "questionSource": "real",
    "contributesToParentReportEvidence": true
  }
]